Workbook

Sheet Opções
A1: Séries das estruturas · vencimento 18/12/2026
A2: Sufixo RTD das opções e ações à vista: | E2: _B_0
A4: Código do campo RTD → | H4: DAT | I4: HOR | J4: ULT | K4: ABE | L4: MAX | M4: MIN | N4: PEX | O4: NEG | P4: VEN
A5: Análise | B5: Perna | C5: Tipo | D5: Strike (análise) | E5: Prêmio teórico | F5: Começa com | G5: Código da série | H5: Data | I5: Hora | J5: Último | K5: Abertura | L5: Máximo | M5: Mínimo | N5: Strike (PEX) | O5: Negócios | P5: Vencimento | Q5: Oferta compra | R5: Oferta venda | S5: Strike confere? | T5: Prêmio usado | U5: Fonte | V5: Sinal | W5: Strike usado | X5: Real − teórico
A6: VALE3 | B6: Compra put | C6: put | D6: 56 | E6: 0.46 | F6: VALEX… | H6: =IF(OR($G6="",H$4=""),"",IFERROR(RTD("RTDTrading.RTDServer",,$G6&$E$2,H$4),"")) | I6: =IF(OR($G6="",I$4=""),"",IFERROR(RTD("RTDTrading.RTDServer",,$G6&$E$2,I$4),"")) | J6: =IF(OR($G6="",J$4=""),"",IFERROR(RTD("RTDTrading.RTDServer",,$G6&$E$2,J$4),"")) | K6: =IF(OR($G6="",K$4=""),"",IFERROR(RTD("RTDTrading.RTDServer",,$G6&$E$2,K$4),"")) | L6: =IF(OR($G6="",L$4=""),"",IFERROR(RTD("RTDTrading.RTDServer",,$G6&$E$2,L$4),"")) | M6: =IF(OR($G6="",M$4=""),"",IFERROR(RTD("RTDTrading.RTDServer",,$G6&$E$2,M$4),"")) | N6: =IF(OR($G6="",N$4=""),"",IFERROR(RTD("RTDTrading.RTDServer",,$G6&$E$2,N$4),"")) | O6: =IF(OR($G6="",O$4=""),"",IFERROR(RTD("RTDTrading.RTDServer",,$G6&$E$2,O$4),"")) | ... R6: =IF(OR($G6="",R$4=""),"",IFERROR(RTD("RTDTrading.RTDServer",,$G6&$E$2,R$4),"")) | S6: =IF(ISNUMBER(N6),IF(ABS(N6-D6)<0.005,"ok","CONFIRA"),"") | T6: =IF(AND(ISNUMBER(Q6),ISNUMBER(R6),Q6>0,R6>0),(Q6+R6)/2,IF(ISNUMBER(J6),J6,E6)) | U6: =IF(AND(ISNUMBER(Q6),ISNUMBER(R6),Q6>0,R6>0),"meio do book",IF(ISNUMBER(J6),"último negócio","teórico")) | V6: =IF(LEFT(B6,5)="Venda",1,-1) | W6: =IF(ISNUMBER(N6),N6,D6) | X6: =T6-E6
A7: VALE3 | B7: Venda put | C7: put | D7: 60 | E7: 1.23 | F7: VALEX… | H7: =IF(OR($G7="",H$4=""),"",IFERROR(RTD("RTDTrading.RTDServer",,$G7&$E$2,H$4),"")) | I7: =IF(OR($G7="",I$4=""),"",IFERROR(RTD("RTDTrading.RTDServer",,$G7&$E$2,I$4),"")) | J7: =IF(OR($G7="",J$4=""),"",IFERROR(RTD("RTDTrading.RTDServer",,$G7&$E$2,J$4),"")) | K7: =IF(OR($G7="",K$4=""),"",IFERROR(RTD("RTDTrading.RTDServer",,$G7&$E$2,K$4),"")) | L7: =IF(OR($G7="",L$4=""),"",IFERROR(RTD("RTDTrading.RTDServer",,$G7&$E$2,L$4),"")) | M7: =IF(OR($G7="",M$4=""),"",IFERROR(RTD("RTDTrading.RTDServer",,$G7&$E$2,M$4),"")) | N7: =IF(OR($G7="",N$4=""),"",IFERROR(RTD("RTDTrading.RTDServer",,$G7&$E$2,N$4),"")) | O7: =IF(OR($G7="",O$4=""),"",IFERROR(RTD("RTDTrading.RTDServer",,$G7&$E$2,O$4),"")) | ... R7: =IF(OR($G7="",R$4=""),"",IFERROR(RTD("RTDTrading.RTDServer",,$G7&$E$2,R$4),"")) | S7: =IF(ISNUMBER(N7),IF(ABS(N7-D7)<0.005,"ok","CONFIRA"),"") | T7: =IF(AND(ISNUMBER(Q7),ISNUMBER(R7),Q7>0,R7>0),(Q7+R7)/2,IF(ISNUMBER(J7),J7,E7)) | U7: =IF(AND(ISNUMBER(Q7),ISNUMBER(R7),Q7>0,R7>0),"meio do book",IF(ISNUMBER(J7),"último negócio","teórico")) | V7: =IF(LEFT(B7,5)="Venda",1,-1) | W7: =IF(ISNUMBER(N7),N7,D7) | X7: =T7-E7
A8: VALE3 | B8: Venda call | C8: call | D8: 70 | E8: 1.79 | F8: VALEL… | H8: =IF(OR($G8="",H$4=""),"",IFERROR(RTD("RTDTrading.RTDServer",,$G8&$E$2,H$4),"")) | I8: =IF(OR($G8="",I$4=""),"",IFERROR(RTD("RTDTrading.RTDServer",,$G8&$E$2,I$4),"")) | J8: =IF(OR($G8="",J$4=""),"",IFERROR(RTD("RTDTrading.RTDServer",,$G8&$E$2,J$4),"")) | K8: =IF(OR($G8="",K$4=""),"",IFERROR(RTD("RTDTrading.RTDServer",,$G8&$E$2,K$4),"")) | L8: =IF(OR($G8="",L$4=""),"",IFERROR(RTD("RTDTrading.RTDServer",,$G8&$E$2,L$4),"")) | M8: =IF(OR($G8="",M$4=""),"",IFERROR(RTD("RTDTrading.RTDServer",,$G8&$E$2,M$4),"")) | N8: =IF(OR($G8="",N$4=""),"",IFERROR(RTD("RTDTrading.RTDServer",,$G8&$E$2,N$4),"")) | O8: =IF(OR($G8="",O$4=""),"",IFERROR(RTD("RTDTrading.RTDServer",,$G8&$E$2,O$4),"")) | ... R8: =IF(OR($G8="",R$4=""),"",IFERROR(RTD("RTDTrading.RTDServer",,$G8&$E$2,R$4),"")) | S8: =IF(ISNUMBER(N8),IF(ABS(N8-D8)<0.005,"ok","CONFIRA"),"") | T8: =IF(AND(ISNUMBER(Q8),ISNUMBER(R8),Q8>0,R8>0),(Q8+R8)/2,IF(ISNUMBER(J8),J8,E8)) | U8: =IF(AND(ISNUMBER(Q8),ISNUMBER(R8),Q8>0,R8>0),"meio do book",IF(ISNUMBER(J8),"último negócio","teórico")) | V8: =IF(LEFT(B8,5)="Venda",1,-1) | W8: =IF(ISNUMBER(N8),N8,D8) | X8: =T8-E8
A9: VALE3 | B9: Compra call | C9: call | D9: 74 | E9: 0.91 | F9: VALEL… | H9: =IF(OR($G9="",H$4=""),"",IFERROR(RTD("RTDTrading.RTDServer",,$G9&$E$2,H$4),"")) | I9: =IF(OR($G9="",I$4=""),"",IFERROR(RTD("RTDTrading.RTDServer",,$G9&$E$2,I$4),"")) | J9: =IF(OR($G9="",J$4=""),"",IFERROR(RTD("RTDTrading.RTDServer",,$G9&$E$2,J$4),"")) | K9: =IF(OR($G9="",K$4=""),"",IFERROR(RTD("RTDTrading.RTDServer",,$G9&$E$2,K$4),"")) | L9: =IF(OR($G9="",L$4=""),"",IFERROR(RTD("RTDTrading.RTDServer",,$G9&$E$2,L$4),"")) | M9: =IF(OR($G9="",M$4=""),"",IFERROR(RTD("RTDTrading.RTDServer",,$G9&$E$2,M$4),"")) | N9: =IF(OR($G9="",N$4=""),"",IFERROR(RTD("RTDTrading.RTDServer",,$G9&$E$2,N$4),"")) | O9: =IF(OR($G9="",O$4=""),"",IFERROR(RTD("RTDTrading.RTDServer",,$G9&$E$2,O$4),"")) | ... R9: =IF(OR($G9="",R$4=""),"",IFERROR(RTD("RTDTrading.RTDServer",,$G9&$E$2,R$4),"")) | S9: =IF(ISNUMBER(N9),IF(ABS(N9-D9)<0.005,"ok","CONFIRA"),"") | T9: =IF(AND(ISNUMBER(Q9),ISNUMBER(R9),Q9>0,R9>0),(Q9+R9)/2,IF(ISNUMBER(J9),J9,E9)) | U9: =IF(AND(ISNUMBER(Q9),ISNUMBER(R9),Q9>0,R9>0),"meio do book",IF(ISNUMBER(J9),"último negócio","teórico")) | V9: =IF(LEFT(B9,5)="Venda",1,-1) | W9: =IF(ISNUMBER(N9),N9,D9) | X9: =T9-E9
A10: PETR4 | B10: Venda put | C10: put | D10: 50 | E10: 1.96 | F10: PETRX… | H10: =IF(OR($G10="",H$4=""),"",IFERROR(RTD("RTDTrading.RTDServer",,$G10&$E$2,H$4),"")) | I10: =IF(OR($G10="",I$4=""),"",IFERROR(RTD("RTDTrading.RTDServer",,$G10&$E$2,I$4),"")) | J10: =IF(OR($G10="",J$4=""),"",IFERROR(RTD("RTDTrading.RTDServer",,$G10&$E$2,J$4),"")) | K10: =IF(OR($G10="",K$4=""),"",IFERROR(RTD("RTDTrading.RTDServer",,$G10&$E$2,K$4),"")) | L10: =IF(OR($G10="",L$4=""),"",IFERROR(RTD("RTDTrading.RTDServer",,$G10&$E$2,L$4),"")) | M10: =IF(OR($G10="",M$4=""),"",IFERROR(RTD("RTDTrading.RTDServer",,$G10&$E$2,M$4),"")) | N10: =IF(OR($G10="",N$4=""),"",IFERROR(RTD("RTDTrading.RTDServer",,$G10&$E$2,N$4),"")) | O10: =IF(OR($G10="",O$4=""),"",IFERROR(RTD("RTDTrading.RTDServer",,$G10&$E$2,O$4),"")) | ... R10: =IF(OR($G10="",R$4=""),"",IFERROR(RTD("RTDTrading.RTDServer",,$G10&$E$2,R$4),"")) | S10: =IF(ISNUMBER(N10),IF(ABS(N10-D10)<0.005,"ok","CONFIRA"),"") | T10: =IF(AND(ISNUMBER(Q10),ISNUMBER(R10),Q10>0,R10>0),(Q10+R10)/2,IF(ISNUMBER(J10),J10,E10)) | U10: =IF(AND(ISNUMBER(Q10),ISNUMBER(R10),Q10>0,R10>0),"meio do book",IF(ISNUMBER(J10),"último negócio","teórico")) | V10: =IF(LEFT(B10,5)="Venda",1,-1) | W10: =IF(ISNUMBER(N10),N10,D10) | X10: =T10-E10
A11: PETR4 | B11: Compra put | C11: put | D11: 46 | E11: 0.89 | F11: PETRX… | H11: =IF(OR($G11="",H$4=""),"",IFERROR(RTD("RTDTrading.RTDServer",,$G11&$E$2,H$4),"")) | I11: =IF(OR($G11="",I$4=""),"",IFERROR(RTD("RTDTrading.RTDServer",,$G11&$E$2,I$4),"")) | J11: =IF(OR($G11="",J$4=""),"",IFERROR(RTD("RTDTrading.RTDServer",,$G11&$E$2,J$4),"")) | K11: =IF(OR($G11="",K$4=""),"",IFERROR(RTD("RTDTrading.RTDServer",,$G11&$E$2,K$4),"")) | L11: =IF(OR($G11="",L$4=""),"",IFERROR(RTD("RTDTrading.RTDServer",,$G11&$E$2,L$4),"")) | M11: =IF(OR($G11="",M$4=""),"",IFERROR(RTD("RTDTrading.RTDServer",,$G11&$E$2,M$4),"")) | N11: =IF(OR($G11="",N$4=""),"",IFERROR(RTD("RTDTrading.RTDServer",,$G11&$E$2,N$4),"")) | O11: =IF(OR($G11="",O$4=""),"",IFERROR(RTD("RTDTrading.RTDServer",,$G11&$E$2,O$4),"")) | ... R11: =IF(OR($G11="",R$4=""),"",IFERROR(RTD("RTDTrading.RTDServer",,$G11&$E$2,R$4),"")) | S11: =IF(ISNUMBER(N11),IF(ABS(N11-D11)<0.005,"ok","CONFIRA"),"") | T11: =IF(AND(ISNUMBER(Q11),ISNUMBER(R11),Q11>0,R11>0),(Q11+R11)/2,IF(ISNUMBER(J11),J11,E11)) | U11: =IF(AND(ISNUMBER(Q11),ISNUMBER(R11),Q11>0,R11>0),"meio do book",IF(ISNUMBER(J11),"último negócio","teórico")) | V11: =IF(LEFT(B11,5)="Venda",1,-1) | W11: =IF(ISNUMBER(N11),N11,D11) | X11: =T11-E11
A12: BBAS3 | B12: Venda call | C12: call | D12: 20 | E12: 1.59 | F12: BBASL… | H12: =IF(OR($G12="",H$4=""),"",IFERROR(RTD("RTDTrading.RTDServer",,$G12&$E$2,H$4),"")) | I12: =IF(OR($G12="",I$4=""),"",IFERROR(RTD("RTDTrading.RTDServer",,$G12&$E$2,I$4),"")) | J12: =IF(OR($G12="",J$4=""),"",IFERROR(RTD("RTDTrading.RTDServer",,$G12&$E$2,J$4),"")) | K12: =IF(OR($G12="",K$4=""),"",IFERROR(RTD("RTDTrading.RTDServer",,$G12&$E$2,K$4),"")) | L12: =IF(OR($G12="",L$4=""),"",IFERROR(RTD("RTDTrading.RTDServer",,$G12&$E$2,L$4),"")) | M12: =IF(OR($G12="",M$4=""),"",IFERROR(RTD("RTDTrading.RTDServer",,$G12&$E$2,M$4),"")) | N12: =IF(OR($G12="",N$4=""),"",IFERROR(RTD("RTDTrading.RTDServer",,$G12&$E$2,N$4),"")) | O12: =IF(OR($G12="",O$4=""),"",IFERROR(RTD("RTDTrading.RTDServer",,$G12&$E$2,O$4),"")) | ... R12: =IF(OR($G12="",R$4=""),"",IFERROR(RTD("RTDTrading.RTDServer",,$G12&$E$2,R$4),"")) | S12: =IF(ISNUMBER(N12),IF(ABS(N12-D12)<0.005,"ok","CONFIRA"),"") | T12: =IF(AND(ISNUMBER(Q12),ISNUMBER(R12),Q12>0,R12>0),(Q12+R12)/2,IF(ISNUMBER(J12),J12,E12)) | U12: =IF(AND(ISNUMBER(Q12),ISNUMBER(R12),Q12>0,R12>0),"meio do book",IF(ISNUMBER(J12),"último negócio","teórico")) | V12: =IF(LEFT(B12,5)="Venda",1,-1) | W12: =IF(ISNUMBER(N12),N12,D12) | X12: =T12-E12
A13: BBAS3 | B13: Compra call | C13: call | D13: 22 | E13: 1.08 | F13: BBASL… | H13: =IF(OR($G13="",H$4=""),"",IFERROR(RTD("RTDTrading.RTDServer",,$G13&$E$2,H$4),"")) | I13: =IF(OR($G13="",I$4=""),"",IFERROR(RTD("RTDTrading.RTDServer",,$G13&$E$2,I$4),"")) | J13: =IF(OR($G13="",J$4=""),"",IFERROR(RTD("RTDTrading.RTDServer",,$G13&$E$2,J$4),"")) | K13: =IF(OR($G13="",K$4=""),"",IFERROR(RTD("RTDTrading.RTDServer",,$G13&$E$2,K$4),"")) | L13: =IF(OR($G13="",L$4=""),"",IFERROR(RTD("RTDTrading.RTDServer",,$G13&$E$2,L$4),"")) | M13: =IF(OR($G13="",M$4=""),"",IFERROR(RTD("RTDTrading.RTDServer",,$G13&$E$2,M$4),"")) | N13: =IF(OR($G13="",N$4=""),"",IFERROR(RTD("RTDTrading.RTDServer",,$G13&$E$2,N$4),"")) | O13: =IF(OR($G13="",O$4=""),"",IFERROR(RTD("RTDTrading.RTDServer",,$G13&$E$2,O$4),"")) | ... R13: =IF(OR($G13="",R$4=""),"",IFERROR(RTD("RTDTrading.RTDServer",,$G13&$E$2,R$4),"")) | S13: =IF(ISNUMBER(N13),IF(ABS(N13-D13)<0.005,"ok","CONFIRA"),"") | T13: =IF(AND(ISNUMBER(Q13),ISNUMBER(R13),Q13>0,R13>0),(Q13+R13)/2,IF(ISNUMBER(J13),J13,E13)) | U13: =IF(AND(ISNUMBER(Q13),ISNUMBER(R13),Q13>0,R13>0),"meio do book",IF(ISNUMBER(J13),"último negócio","teórico")) | V13: =IF(LEFT(B13,5)="Venda",1,-1) | W13: =IF(ISNUMBER(N13),N13,D13) | X13: =T13-E13
A14: BBDC4 | B14: Venda put | C14: put | D14: 14 | E14: 0.9 | F14: BBDCX… | H14: =IF(OR($G14="",H$4=""),"",IFERROR(RTD("RTDTrading.RTDServer",,$G14&$E$2,H$4),"")) | I14: =IF(OR($G14="",I$4=""),"",IFERROR(RTD("RTDTrading.RTDServer",,$G14&$E$2,I$4),"")) | J14: =IF(OR($G14="",J$4=""),"",IFERROR(RTD("RTDTrading.RTDServer",,$G14&$E$2,J$4),"")) | K14: =IF(OR($G14="",K$4=""),"",IFERROR(RTD("RTDTrading.RTDServer",,$G14&$E$2,K$4),"")) | L14: =IF(OR($G14="",L$4=""),"",IFERROR(RTD("RTDTrading.RTDServer",,$G14&$E$2,L$4),"")) | M14: =IF(OR($G14="",M$4=""),"",IFERROR(RTD("RTDTrading.RTDServer",,$G14&$E$2,M$4),"")) | N14: =IF(OR($G14="",N$4=""),"",IFERROR(RTD("RTDTrading.RTDServer",,$G14&$E$2,N$4),"")) | O14: =IF(OR($G14="",O$4=""),"",IFERROR(RTD("RTDTrading.RTDServer",,$G14&$E$2,O$4),"")) | ... R14: =IF(OR($G14="",R$4=""),"",IFERROR(RTD("RTDTrading.RTDServer",,$G14&$E$2,R$4),"")) | S14: =IF(ISNUMBER(N14),IF(ABS(N14-D14)<0.005,"ok","CONFIRA"),"") | T14: =IF(AND(ISNUMBER(Q14),ISNUMBER(R14),Q14>0,R14>0),(Q14+R14)/2,IF(ISNUMBER(J14),J14,E14)) | U14: =IF(AND(ISNUMBER(Q14),ISNUMBER(R14),Q14>0,R14>0),"meio do book",IF(ISNUMBER(J14),"último negócio","teórico")) | V14: =IF(LEFT(B14,5)="Venda",1,-1) | W14: =IF(ISNUMBER(N14),N14,D14) | X14: =T14-E14
A15: PRIO3 | B15: Compra call | C15: call | D15: 72 | E15: 4.02 | F15: PRIOL… | H15: =IF(OR($G15="",H$4=""),"",IFERROR(RTD("RTDTrading.RTDServer",,$G15&$E$2,H$4),"")) | I15: =IF(OR($G15="",I$4=""),"",IFERROR(RTD("RTDTrading.RTDServer",,$G15&$E$2,I$4),"")) | J15: =IF(OR($G15="",J$4=""),"",IFERROR(RTD("RTDTrading.RTDServer",,$G15&$E$2,J$4),"")) | K15: =IF(OR($G15="",K$4=""),"",IFERROR(RTD("RTDTrading.RTDServer",,$G15&$E$2,K$4),"")) | L15: =IF(OR($G15="",L$4=""),"",IFERROR(RTD("RTDTrading.RTDServer",,$G15&$E$2,L$4),"")) | M15: =IF(OR($G15="",M$4=""),"",IFERROR(RTD("RTDTrading.RTDServer",,$G15&$E$2,M$4),"")) | N15: =IF(OR($G15="",N$4=""),"",IFERROR(RTD("RTDTrading.RTDServer",,$G15&$E$2,N$4),"")) | O15: =IF(OR($G15="",O$4=""),"",IFERROR(RTD("RTDTrading.RTDServer",,$G15&$E$2,O$4),"")) | ... R15: =IF(OR($G15="",R$4=""),"",IFERROR(RTD("RTDTrading.RTDServer",,$G15&$E$2,R$4),"")) | S15: =IF(ISNUMBER(N15),IF(ABS(N15-D15)<0.005,"ok","CONFIRA"),"") | T15: =IF(AND(ISNUMBER(Q15),ISNUMBER(R15),Q15>0,R15>0),(Q15+R15)/2,IF(ISNUMBER(J15),J15,E15)) | U15: =IF(AND(ISNUMBER(Q15),ISNUMBER(R15),Q15>0,R15>0),"meio do book",IF(ISNUMBER(J15),"último negócio","teórico")) | V15: =IF(LEFT(B15,5)="Venda",1,-1) | W15: =IF(ISNUMBER(N15),N15,D15) | X15: =T15-E15
A16: PRIO3 | B16: Venda call | C16: call | D16: 78 | E16: 1.8 | F16: PRIOL… | H16: =IF(OR($G16="",H$4=""),"",IFERROR(RTD("RTDTrading.RTDServer",,$G16&$E$2,H$4),"")) | I16: =IF(OR($G16="",I$4=""),"",IFERROR(RTD("RTDTrading.RTDServer",,$G16&$E$2,I$4),"")) | J16: =IF(OR($G16="",J$4=""),"",IFERROR(RTD("RTDTrading.RTDServer",,$G16&$E$2,J$4),"")) | K16: =IF(OR($G16="",K$4=""),"",IFERROR(RTD("RTDTrading.RTDServer",,$G16&$E$2,K$4),"")) | L16: =IF(OR($G16="",L$4=""),"",IFERROR(RTD("RTDTrading.RTDServer",,$G16&$E$2,L$4),"")) | M16: =IF(OR($G16="",M$4=""),"",IFERROR(RTD("RTDTrading.RTDServer",,$G16&$E$2,M$4),"")) | N16: =IF(OR($G16="",N$4=""),"",IFERROR(RTD("RTDTrading.RTDServer",,$G16&$E$2,N$4),"")) | O16: =IF(OR($G16="",O$4=""),"",IFERROR(RTD("RTDTrading.RTDServer",,$G16&$E$2,O$4),"")) | ... R16: =IF(OR($G16="",R$4=""),"",IFERROR(RTD("RTDTrading.RTDServer",,$G16&$E$2,R$4),"")) | S16: =IF(ISNUMBER(N16),IF(ABS(N16-D16)<0.005,"ok","CONFIRA"),"") | T16: =IF(AND(ISNUMBER(Q16),ISNUMBER(R16),Q16>0,R16>0),(Q16+R16)/2,IF(ISNUMBER(J16),J16,E16)) | U16: =IF(AND(ISNUMBER(Q16),ISNUMBER(R16),Q16>0,R16>0),"meio do book",IF(ISNUMBER(J16),"último negócio","teórico")) | V16: =IF(LEFT(B16,5)="Venda",1,-1) | W16: =IF(ISNUMBER(N16),N16,D16) | X16: =T16-E16
A18: Prêmio usado: meio do book (média das ofertas de compra e de venda) quando houver ofertas; senão o último negócio; senão o prêmio teórico da análise.
A19: Strike e prêmio teórico: análises de 26/10/2026 do opcionando.com.br (Black-Scholes, Selic 14% a.a., vencimento 18/12/2026).
A21: Ativos-objeto
A22: Ativo | B22: Último | C22: Máximo | D22: Mínimo | E22: Negócios | F22: Data | G22: Hora
A23: VALE3 | B23: =IFERROR(RTD("RTDTrading.RTDServer",,$A23&$E$2,"ULT"),"") | C23: =IFERROR(RTD("RTDTrading.RTDServer",,$A23&$E$2,"MAX"),"") | D23: =IFERROR(RTD("RTDTrading.RTDServer",,$A23&$E$2,"MIN"),"") | E23: =IFERROR(RTD("RTDTrading.RTDServer",,$A23&$E$2,"NEG"),"") | F23: =IFERROR(RTD("RTDTrading.RTDServer",,$A23&$E$2,"DAT"),"") | G23: =IFERROR(RTD("RTDTrading.RTDServer",,$A23&$E$2,"HOR"),"")
A24: PETR4 | B24: =IFERROR(RTD("RTDTrading.RTDServer",,$A24&$E$2,"ULT"),"") | C24: =IFERROR(RTD("RTDTrading.RTDServer",,$A24&$E$2,"MAX"),"") | D24: =IFERROR(RTD("RTDTrading.RTDServer",,$A24&$E$2,"MIN"),"") | E24: =IFERROR(RTD("RTDTrading.RTDServer",,$A24&$E$2,"NEG"),"") | F24: =IFERROR(RTD("RTDTrading.RTDServer",,$A24&$E$2,"DAT"),"") | G24: =IFERROR(RTD("RTDTrading.RTDServer",,$A24&$E$2,"HOR"),"")
A25: BBAS3 | B25: =IFERROR(RTD("RTDTrading.RTDServer",,$A25&$E$2,"ULT"),"") | C25: =IFERROR(RTD("RTDTrading.RTDServer",,$A25&$E$2,"MAX"),"") | D25: =IFERROR(RTD("RTDTrading.RTDServer",,$A25&$E$2,"MIN"),"") | E25: =IFERROR(RTD("RTDTrading.RTDServer",,$A25&$E$2,"NEG"),"") | F25: =IFERROR(RTD("RTDTrading.RTDServer",,$A25&$E$2,"DAT"),"") | G25: =IFERROR(RTD("RTDTrading.RTDServer",,$A25&$E$2,"HOR"),"")
A26: BBDC4 | B26: =IFERROR(RTD("RTDTrading.RTDServer",,$A26&$E$2,"ULT"),"") | C26: =IFERROR(RTD("RTDTrading.RTDServer",,$A26&$E$2,"MAX"),"") | D26: =IFERROR(RTD("RTDTrading.RTDServer",,$A26&$E$2,"MIN"),"") | E26: =IFERROR(RTD("RTDTrading.RTDServer",,$A26&$E$2,"NEG"),"") | F26: =IFERROR(RTD("RTDTrading.RTDServer",,$A26&$E$2,"DAT"),"") | G26: =IFERROR(RTD("RTDTrading.RTDServer",,$A26&$E$2,"HOR"),"")
A27: PRIO3 | B27: =IFERROR(RTD("RTDTrading.RTDServer",,$A27&$E$2,"ULT"),"") | C27: =IFERROR(RTD("RTDTrading.RTDServer",,$A27&$E$2,"MAX"),"") | D27: =IFERROR(RTD("RTDTrading.RTDServer",,$A27&$E$2,"MIN"),"") | E27: =IFERROR(RTD("RTDTrading.RTDServer",,$A27&$E$2,"NEG"),"") | F27: =IFERROR(RTD("RTDTrading.RTDServer",,$A27&$E$2,"DAT"),"") | G27: =IFERROR(RTD("RTDTrading.RTDServer",,$A27&$E$2,"HOR"),"")

Sheet Leia-me
A1: Opcionando · Cotações das estruturas via RTD do Profit
A3: Como usar
A4: 1. Abra o Profit e mantenha-o conectado. Abra esta planilha no Excel (no Windows, onde o Profit está instalado).
A5: 2. Na aba "Opções", preencha só as células AMARELAS da coluna "Código da série" com o código de cada opção (ex.: VALEL804).
A6: A coluna "Começa com" mostra a raiz e a letra de dezembro: calls de dezembro usam L e puts de dezembro usam X.
A7: 3. Confira a coluna "Strike confere?": se aparecer "CONFIRA", o código digitado não tem o strike da análise.
A8: 4. Os campos de oferta de compra e de venda estão em branco na linha 4 da aba "Opções" (células amarelas).
A9: Copie do Profit o código RTD desses dois campos e cole nelas. Os demais códigos (ULT, PEX, NEG...) vieram da sua lista.
A10: 5. A aba "Estruturas" recalcula crédito, débito, perda máxima, ganho máximo e equilíbrio com os prêmios reais.
A11: Enquanto não houver cotação, ela usa o prêmio teórico (Black-Scholes) da análise e indica isso na coluna "Fonte".
A12: 6. Salve o arquivo (os últimos valores ficam gravados) e me envie. Eu atualizo as análises do site.
A14: Legenda de cores
... A19: Observação: as fórmulas RTD só retornam valores no Excel do Windows com o Profit aberto. Em outro programa, as células aparecem vazias ou com erro.

Sheet Estruturas
A1: Estruturas recalculadas com os prêmios reais
A2: Valores por lote de 100 opções. Positivo = crédito recebido; negativo = débito pago.
A4: Análise | B4: Estrutura | C4: Montagem real (R$/ação) | D4: Montagem teórica (R$/ação) | E4: Diferença | F4: Montagem real (R$/lote) | G4: Ganho máximo (R$/lote) | H4: Perda máxima (R$/lote) | I4: Equilíbrio inferior | J4: Equilíbrio superior | K4: Fonte dos prêmios | L4: Preço do ativo
A5: VALE3 | B5: Iron condor 56/60/70/74 | C5: =SUMPRODUCT(('Opções'!$A$6:$A$16=$A5)*'Opções'!$V$6:$V$16*'Opções'!$T$6:$T$16) | D5: =SUMPRODUCT(('Opções'!$A$6:$A$16=$A5)*'Opções'!$V$6:$V$16*'Opções'!$E$6:$E$16) | E5: =C5-D5 | F5: =C5*100 | G5: =C5*100 | H5: =-(MAX('Opções'!$W$7-'Opções'!$W$6,'Opções'!$W$9-'Opções'!$W$8)-C5)*100 | I5: ='Opções'!$W$7-C5 | J5: ='Opções'!$W$8+C5 | K5: =IF(COUNTIF('Opções'!$U$6:$U$9,"teórico")=4,"teórico",IF(COUNTIF('Opções'!$U$6:$U$9,"teórico")=0,"real","parcial")) | L5: =IFERROR('Opções'!$B$23*1,"")
A6: PETR4 | B6: Trava de alta com put 50/46 | C6: =SUMPRODUCT(('Opções'!$A$6:$A$16=$A6)*'Opções'!$V$6:$V$16*'Opções'!$T$6:$T$16) | D6: =SUMPRODUCT(('Opções'!$A$6:$A$16=$A6)*'Opções'!$V$6:$V$16*'Opções'!$E$6:$E$16) | E6: =C6-D6 | F6: =C6*100 | G6: =C6*100 | H6: =-(('Opções'!$W$10-'Opções'!$W$11)-C6)*100 | I6: ='Opções'!$W$10-C6 | J6: ="" | K6: =IF(COUNTIF('Opções'!$U$10:$U$11,"teórico")=2,"teórico",IF(COUNTIF('Opções'!$U$10:$U$11,"teórico")=0,"real","parcial")) | L6: =IFERROR('Opções'!$B$24*1,"")
A7: BBAS3 | B7: Trava de baixa com call 20/22 | C7: =SUMPRODUCT(('Opções'!$A$6:$A$16=$A7)*'Opções'!$V$6:$V$16*'Opções'!$T$6:$T$16) | D7: =SUMPRODUCT(('Opções'!$A$6:$A$16=$A7)*'Opções'!$V$6:$V$16*'Opções'!$E$6:$E$16) | E7: =C7-D7 | F7: =C7*100 | G7: =C7*100 | H7: =-(('Opções'!$W$13-'Opções'!$W$12)-C7)*100 | I7: ="" | J7: ='Opções'!$W$12+C7 | K7: =IF(COUNTIF('Opções'!$U$12:$U$13,"teórico")=2,"teórico",IF(COUNTIF('Opções'!$U$12:$U$13,"teórico")=0,"real","parcial")) | L7: =IFERROR('Opções'!$B$25*1,"")
A8: BBDC4 | B8: Venda de put coberta 14 | C8: =SUMPRODUCT(('Opções'!$A$6:$A$16=$A8)*'Opções'!$V$6:$V$16*'Opções'!$T$6:$T$16) | D8: =SUMPRODUCT(('Opções'!$A$6:$A$16=$A8)*'Opções'!$V$6:$V$16*'Opções'!$E$6:$E$16) | E8: =C8-D8 | F8: =C8*100 | G8: =C8*100 | H8: =-('Opções'!$W$14-C8)*100 | I8: ='Opções'!$W$14-C8 | J8: ="" | K8: =IF(COUNTIF('Opções'!$U$14:$U$14,"teórico")=1,"teórico",IF(COUNTIF('Opções'!$U$14:$U$14,"teórico")=0,"real","parcial")) | L8: =IFERROR('Opções'!$B$26*1,"")
A9: PRIO3 | B9: Trava de alta com call 72/78 | C9: =SUMPRODUCT(('Opções'!$A$6:$A$16=$A9)*'Opções'!$V$6:$V$16*'Opções'!$T$6:$T$16) | D9: =SUMPRODUCT(('Opções'!$A$6:$A$16=$A9)*'Opções'!$V$6:$V$16*'Opções'!$E$6:$E$16) | E9: =C9-D9 | F9: =C9*100 | G9: =(('Opções'!$W$16-'Opções'!$W$15)+C9)*100 | H9: =C9*100 | I9: ='Opções'!$W$15-C9 | J9: ="" | K9: =IF(COUNTIF('Opções'!$U$15:$U$16,"teórico")=2,"teórico",IF(COUNTIF('Opções'!$U$15:$U$16,"teórico")=0,"real","parcial")) | L9: =IFERROR('Opções'!$B$27*1,"")
A11: Perda máxima da put coberta (BBDC4): caixa comprometido se a ação for a zero, isto é, (strike − prêmio) × 100.
A12: Fonte "teórico": nenhuma perna com cotação ainda; "parcial": parte das pernas com cotação real; "real": todas com cotação.
